[
    {
        "doc_id": 1309,
        "sentences": [
            "Sizda qanday qarashlar bar ?",
            "bu bek qorqunchlu q , me n bu oyunni yaxshi köretti m , emma her ikki minutta dégüdek uni küldüridighan élanlar bar ."
        ],
        "replies": [
            -1,
            0
        ],
        "speakers": [
            0,
            1
        ],
        "sentence_ids": [
            0,
            0,
            0,
            0,
            0,
            1,
            1,
            1,
            1,
            1,
            1,
            1,
            1,
            1,
            1,
            1,
            1,
            1,
            1,
            1,
            1,
            1,
            1,
            1,
            1,
            1,
            1,
            1
        ],
        "triplets": [
            [
                13,
                14,
                -1,
                -1,
                14,
                17,
                "pos",
                "oyunni",
                "",
                "yaxshi körettim"
            ],
            [
                13,
                14,
                24,
                26,
                6,
                9,
                "neg",
                "oyunni",
                "küldüridighan élanlar",
                "bek qorqunchluq"
            ]
        ],
        "targets": [
            [
                13,
                14,
                "oyunni"
            ]
        ],
        "aspects": [
            [
                24,
                26,
                "küldüridighan élanlar"
            ]
        ],
        "opinions": [
            [
                14,
                17,
                "yaxshi körettim",
                "pos"
            ],
            [
                6,
                9,
                "bek qorqunchluq",
                "neg"
            ]
        ],
        "adj": [
            [
                [
                    0.0,
                    0.0,
                    1.0,
                    0.0,
                    0.0
                ],
                [
                    0.0,
                    0.0,
                    1.0,
                    0.0,
                    0.0
                ],
                [
                    1.0,
                    1.0,
                    0.0,
                    1.0,
                    1.0
                ],
                [
                    0.0,
                    0.0,
                    1.0,
                    0.0,
                    0.0
                ],
                [
                    0.0,
                    0.0,
                    1.0,
                    0.0,
                    0.0
                ]
            ],
            [
                [
                    0.0,
                    0.0,
                    1.0,
                    0.0,
                    0.0,
                    0.0,
                    0.0,
                    0.0,
                    0.0,
                    0.0,
                    0.0,
                    0.0,
                    0.0,
                    0.0,
                    0.0,
                    0.0,
                    0.0,
                    0.0,
                    0.0,
                    0.0,
                    0.0,
                    0.0,
                    0.0
                ],
                [
                    0.0,
                    0.0,
                    1.0,
                    0.0,
                    0.0,
                    0.0,
                    0.0,
                    0.0,
                    0.0,
                    0.0,
                    0.0,
                    0.0,
                    0.0,
                    0.0,
                    0.0,
                    0.0,
                    0.0,
                    0.0,
                    0.0,
                    0.0,
                    0.0,
                    0.0,
                    0.0
                ],
                [
                    1.0,
                    1.0,
                    0.0,
                    1.0,
                    1.0,
                    1.0,
                    1.0,
                    0.0,
                    0.0,
                    0.0,
                    0.0,
                    0.0,
                    0.0,
                    0.0,
                    0.0,
                    0.0,
                    0.0,
                    0.0,
                    0.0,
                    0.0,
                    0.0,
                    0.0,
                    0.0
                ],
                [
                    0.0,
                    0.0,
                    1.0,
                    0.0,
                    0.0,
                    0.0,
                    0.0,
                    0.0,
                    0.0,
                    0.0,
                    0.0,
                    0.0,
                    0.0,
                    0.0,
                    0.0,
                    0.0,
                    0.0,
                    0.0,
                    0.0,
                    0.0,
                    0.0,
                    0.0,
                    0.0
                ],
                [
                    0.0,
                    0.0,
                    1.0,
                    0.0,
                    0.0,
                    0.0,
                    0.0,
                    0.0,
                    0.0,
                    0.0,
                    0.0,
                    0.0,
                    0.0,
                    0.0,
                    0.0,
                    0.0,
                    0.0,
                    0.0,
                    0.0,
                    0.0,
                    0.0,
                    0.0,
                    0.0
                ],
                [
                    0.0,
                    0.0,
                    1.0,
                    0.0,
                    0.0,
                    0.0,
                    0.0,
                    0.0,
                    0.0,
                    0.0,
                    0.0,
                    0.0,
                    0.0,
                    0.0,
                    0.0,
                    0.0,
                    0.0,
                    0.0,
                    0.0,
                    0.0,
                    0.0,
                    0.0,
                    0.0
                ],
                [
                    0.0,
                    0.0,
                    1.0,
                    0.0,
                    0.0,
                    0.0,
                    0.0,
                    0.0,
                    0.0,
                    0.0,
                    0.0,
                    0.0,
                    0.0,
                    0.0,
                    0.0,
                    0.0,
                    0.0,
                    0.0,
                    0.0,
                    0.0,
                    0.0,
                    0.0,
                    0.0
                ],
                [
                    0.0,
                    0.0,
                    0.0,
                    0.0,
                    0.0,
                    0.0,
                    0.0,
                    0.0,
                    0.0,
                    0.0,
                    0.0,
                    0.0,
                    0.0,
                    0.0,
                    0.0,
                    0.0,
                    0.0,
                    0.0,
                    0.0,
                    0.0,
                    1.0,
                    0.0,
                    0.0
                ],
                [
                    0.0,
                    0.0,
                    0.0,
                    0.0,
                    0.0,
                    0.0,
                    0.0,
                    0.0,
                    0.0,
                    0.0,
                    1.0,
                    0.0,
                    0.0,
                    0.0,
                    0.0,
                    0.0,
                    0.0,
                    0.0,
                    0.0,
                    0.0,
                    0.0,
                    0.0,
                    0.0
                ],
                [
                    0.0,
                    0.0,
                    0.0,
                    0.0,
                    0.0,
                    0.0,
                    0.0,
                    0.0,
                    0.0,
                    0.0,
                    1.0,
                    0.0,
                    0.0,
                    0.0,
                    0.0,
                    0.0,
                    0.0,
                    0.0,
                    0.0,
                    0.0,
                    0.0,
                    0.0,
                    0.0
                ],
                [
                    0.0,
                    0.0,
                    0.0,
                    0.0,
                    0.0,
                    0.0,
                    0.0,
                    0.0,
                    1.0,
                    1.0,
                    0.0,
                    1.0,
                    0.0,
                    1.0,
                    0.0,
                    0.0,
                    0.0,
                    1.0,
                    0.0,
                    0.0,
                    1.0,
                    0.0,
                    1.0
                ],
                [
                    0.0,
                    0.0,
                    0.0,
                    0.0,
                    0.0,
                    0.0,
                    0.0,
                    0.0,
                    0.0,
                    0.0,
                    1.0,
                    0.0,
                    0.0,
                    0.0,
                    0.0,
                    0.0,
                    0.0,
                    0.0,
                    0.0,
                    0.0,
                    0.0,
                    0.0,
                    0.0
                ],
                [
                    0.0,
                    0.0,
                    0.0,
                    0.0,
                    0.0,
                    0.0,
                    0.0,
                    0.0,
                    0.0,
                    0.0,
                    0.0,
                    0.0,
                    0.0,
                    1.0,
                    0.0,
                    0.0,
                    0.0,
                    0.0,
                    0.0,
                    0.0,
                    0.0,
                    0.0,
                    0.0
                ],
                [
                    0.0,
                    0.0,
                    0.0,
                    0.0,
                    0.0,
                    0.0,
                    0.0,
                    0.0,
                    0.0,
                    0.0,
                    1.0,
                    0.0,
                    1.0,
                    0.0,
                    1.0,
                    1.0,
                    1.0,
                    0.0,
                    0.0,
                    0.0,
                    0.0,
                    0.0,
                    0.0
                ],
                [
                    0.0,
                    0.0,
                    0.0,
                    0.0,
                    0.0,
                    0.0,
                    0.0,
                    0.0,
                    0.0,
                    0.0,
                    0.0,
                    0.0,
                    0.0,
                    1.0,
                    0.0,
                    0.0,
                    0.0,
                    0.0,
                    0.0,
                    0.0,
                    0.0,
                    0.0,
                    0.0
                ],
                [
                    0.0,
                    0.0,
                    0.0,
                    0.0,
                    0.0,
                    0.0,
                    0.0,
                    0.0,
                    0.0,
                    0.0,
                    0.0,
                    0.0,
                    0.0,
                    1.0,
                    0.0,
                    0.0,
                    0.0,
                    0.0,
                    0.0,
                    0.0,
                    0.0,
                    0.0,
                    0.0
                ],
                [
                    0.0,
                    0.0,
                    0.0,
                    0.0,
                    0.0,
                    0.0,
                    0.0,
                    0.0,
                    0.0,
                    0.0,
                    0.0,
                    0.0,
                    0.0,
                    1.0,
                    0.0,
                    0.0,
                    0.0,
                    0.0,
                    0.0,
                    0.0,
                    0.0,
                    0.0,
                    0.0
                ],
                [
                    0.0,
                    0.0,
                    0.0,
                    0.0,
                    0.0,
                    0.0,
                    0.0,
                    0.0,
                    0.0,
                    0.0,
                    1.0,
                    0.0,
                    0.0,
                    0.0,
                    0.0,
                    0.0,
                    0.0,
                    0.0,
                    1.0,
                    1.0,
                    0.0,
                    0.0,
                    0.0
                ],
                [
                    0.0,
                    0.0,
                    0.0,
                    0.0,
                    0.0,
                    0.0,
                    0.0,
                    0.0,
                    0.0,
                    0.0,
                    0.0,
                    0.0,
                    0.0,
                    0.0,
                    0.0,
                    0.0,
                    0.0,
                    1.0,
                    0.0,
                    0.0,
                    0.0,
                    0.0,
                    0.0
                ],
                [
                    0.0,
                    0.0,
                    0.0,
                    0.0,
                    0.0,
                    0.0,
                    0.0,
                    0.0,
                    0.0,
                    0.0,
                    0.0,
                    0.0,
                    0.0,
                    0.0,
                    0.0,
                    0.0,
                    0.0,
                    1.0,
                    0.0,
                    0.0,
                    0.0,
                    0.0,
                    0.0
                ],
                [
                    0.0,
                    0.0,
                    0.0,
                    0.0,
                    0.0,
                    0.0,
                    0.0,
                    1.0,
                    0.0,
                    0.0,
                    1.0,
                    0.0,
                    0.0,
                    0.0,
                    0.0,
                    0.0,
                    0.0,
                    0.0,
                    0.0,
                    0.0,
                    0.0,
                    1.0,
                    0.0
                ],
                [
                    0.0,
                    0.0,
                    0.0,
                    0.0,
                    0.0,
                    0.0,
                    0.0,
                    0.0,
                    0.0,
                    0.0,
                    0.0,
                    0.0,
                    0.0,
                    0.0,
                    0.0,
                    0.0,
                    0.0,
                    0.0,
                    0.0,
                    0.0,
                    1.0,
                    0.0,
                    0.0
                ],
                [
                    0.0,
                    0.0,
                    0.0,
                    0.0,
                    0.0,
                    0.0,
                    0.0,
                    0.0,
                    0.0,
                    0.0,
                    1.0,
                    0.0,
                    0.0,
                    0.0,
                    0.0,
                    0.0,
                    0.0,
                    0.0,
                    0.0,
                    0.0,
                    0.0,
                    0.0,
                    0.0
                ]
            ]
        ],
        "words": [
            [
                "Sizda",
                "qanday",
                "qarashlar",
                "bar",
                "?"
            ],
            [
                "bu",
                "bek",
                "qorqunchlu",
                "q",
                ",",
                "me",
                "n",
                "bu",
                "oyunni",
                "yaxshi",
                "köretti",
                "m",
                ",",
                "emma",
                "her",
                "ikki",
                "minutta",
                "dégüdek",
                "uni",
                "küldüridighan",
                "élanlar",
                "bar",
                "."
            ]
        ],
        "pos": [
            [
                "NOUN N",
                "NOUN N",
                "NOUN N",
                "PUNCT Y",
                "PUNCT Y"
            ],
            [
                "PUNCT N",
                "NOUN N",
                "NOUN N",
                "PUNCT N",
                "PUNCT N",
                "PUNCT Y",
                "PUNCT Y",
                "PUNCT N",
                "NOUN N",
                "NOUN N",
                "NOUN N",
                "PUNCT N",
                "PUNCT N",
                "NOUN N",
                "PUNCT N",
                "PUNCT N",
                "NOUN N",
                "NOUN N",
                "PUNCT N",
                "NOUN N",
                "NOUN N",
                "PUNCT N",
                "PUNCT Y"
            ]
        ]
    }
]